AstroToolkit/Aliases.py
AstroToolkit/Config.py
AstroToolkit/Datapages.py
AstroToolkit/Epochs.py
AstroToolkit/Gui.py
AstroToolkit/Models.py
AstroToolkit/Overlays.py
AstroToolkit/PackageInfo.py
AstroToolkit/Tools.py
AstroToolkit/Utility.py
AstroToolkit/Configuration/baseconfig.py
AstroToolkit/Configuration/catalogue_setup.py
AstroToolkit/Configuration/epochs.py
AstroToolkit/Configuration/overlays.py
AstroToolkit/Data/bin_lightcurves.py
AstroToolkit/Data/bulkquery.py
AstroToolkit/Data/crop_lightcurves.py
AstroToolkit/Data/dataquery.py
AstroToolkit/Data/fetch_crts.py
AstroToolkit/Data/fetch_tess.py
AstroToolkit/Data/hrdquery.py
AstroToolkit/Data/imageoverlay.py
AstroToolkit/Data/imagequery.py
AstroToolkit/Data/lightcurvequery.py
AstroToolkit/Data/reddeningquery.py
AstroToolkit/Data/sedquery.py
AstroToolkit/Data/sigmaclip.py
AstroToolkit/Data/simbad_query.py
AstroToolkit/Data/spectrumquery.py
AstroToolkit/DatapageElements/datapage_buttons.py
AstroToolkit/DatapageElements/metadata_table.py
AstroToolkit/Examples/AR_Sco_TNT.txt
AstroToolkit/Examples/datapage_creation.py
AstroToolkit/Examples/datapage_hrd.fits
AstroToolkit/Examples/datapage_image.fits
AstroToolkit/Examples/datapage_lightcurve.fits
AstroToolkit/Examples/datapage_sed.fits
AstroToolkit/Examples/datapage_spectrum.fits
AstroToolkit/Examples/examples_utilities.py
AstroToolkit/Examples/external_data.py
AstroToolkit/Examples/fetching_data.py
AstroToolkit/Examples/image_overlays.fits
AstroToolkit/Examples/image_plotting.py
AstroToolkit/Examples/lightcurve.fits
AstroToolkit/Examples/lightcurve_plotting.py
AstroToolkit/Examples/loadExamples.py
AstroToolkit/Examples/local_files.py
AstroToolkit/Examples/test_data.fits
AstroToolkit/Examples/test_lightcurve.fits
AstroToolkit/Examples/user_defined_overlay.py
AstroToolkit/FileHandling/file_naming.py
AstroToolkit/FileHandling/file_reading.py
AstroToolkit/FileHandling/file_writing.py
AstroToolkit/Input/input_validation.py
AstroToolkit/Misc/coordinate_conversions.py
astrotoolkit-1.7.1.dist-info/licenses/LICENSE
astrotoolkit-1.7.1.dist-info/METADATA
astrotoolkit-1.7.1.dist-info/WHEEL
astrotoolkit-1.7.1.dist-info/entry_points.txt
astrotoolkit-1.7.1.dist-info/top_level.txt
astrotoolkit-1.7.1.dist-info/RECORD
